{"id": 10506, "source_id": "a081039b-875f-4bec-9d39-7dedfe54c201", "company_name": "Rumah Sakit Umum Pusat Fatmawati Jakarta", "province": "DKI JAKARTA", "city": "KOTA ADM. JAKARTA SELATAN", "recommended_degree": "Administrasi Rumah Sakit, Ilmu Komunikasi, Administrasi (Diploma)", "job_title": "Front Office Staf", "job_description": "Memberikan pelayanan terkait dengan proses registrasi, pembayaran, dan pemberian informasi kepada pasien, keluarga dan pengunjung untuk memastikan bahwa kualitas pelayanan yang diterima oleh pasien, keluarga, dan pengunjung konsisten sesuai dengan standar yang diberlakukan oleh Rumah Sakit", "application_deadline": "2025-12-07", "quota": 4, "registered": 26, "position_type": "Front Office Staf", "government_agency": "Kementerian Kesehatan", "sub_government_agency": "Rumah Sakit Umum Pusat Fatmawati Jakarta", "angkatan": "3", "tahun": "2025"}