{"id": 11138, "source_id": "a07442f3-82b2-442e-a2d7-371dab230b59", "company_name": "Graha Andrasentra Propertindo", "province": "JAWA BARAT", "city": "KOTA BOGOR", "recommended_degree": "Akuntansi, Manajemen Keuangan (Sarjana)", "job_title": "Finance Support", "job_description": "Penempatan : Office di Sentul City\nTugas Utama:\nMendukung tim Keuangan dalam memastikan keakuratan pencatatan transaksi harian, mengelola arus kas operasional themepark, serta membantu dalam proses budgeting dan pelaporan keuangan.\nTanggung Jawab:\n1. Membantu pencatatan dan verifikasi semua transaksi operasional harian\n2. Memastikan General Ledger (GL) yang terkait dengan pendapatan telah tercatat dengan benar.\n3. Melakukan rekonsiliasi kas harian antara laporan sistem penjualan (Point of Sale/POS) dengan setoran fisik yang diterima.\n4. Membantu dalam proses petty cash (kas kecil) untuk kebutuhan operasional darurat themepark.\n5. Membantu menyiapkan laporan keuangan mingguan dan bulanan. \n6. Mengumpulkan data yang diperlukan untuk proses penyusunan anggaran (budgeting) dan peramalan (forecasting) operasional themepark.\n7. Mengarsip dan menata semua dokumen keuangan (faktur, voucher, bukti kas masuk/keluar) agar mudah diakses saat diperlukan untuk keperluan audit atau verifikasi.\"", "application_deadline": "2025-12-07", "quota": 1, "registered": 4, "position_type": "Finance Support", "government_agency": null, "sub_government_agency": null, "angkatan": "3", "tahun": "2025"}