{"id": 11996, "source_id": "a080b1a2-2d01-46fb-997d-b52e2cc93aff", "company_name": "Ragdalion Revolusi Industri", "province": "JAWA BARAT", "city": "KAB. BEKASI", "recommended_degree": "Teknik Mekatronika, Teknik Industri, Rekayasa Teknologi Manufaktur, Teknik Informatika, Sistem Informasi (Diploma, Sarjana)", "job_title": "System Analyst", "job_description": "1. Mengumpulkan dan menganalisis kebutuhan sistem dari stakeholder atau user.\n2. Membuat dokumen BRD (Business Requirement Document) dan FRD (Functional Requirement Document).\n3. Mendesain alur proses sistem menggunakan flowchart, BPMN, dan diagram lainnya.\n4. Menyusun desain teknis seperti ERD, arsitektur sistem, dan spesifikasi API.\n5. Menerjemahkan kebutuhan bisnis menjadi requirement teknis untuk tim developer.\n6. Berkoordinasi dengan tim UI/UX untuk memastikan desain fitur sesuai kebutuhan sistem.\n7. Melakukan komunikasi rutin dengan klien atau user untuk validasi requirement.\n8. Mendukung proses SIT dan UAT dengan menyusun skenario pengujian dan acceptance criteria.\n9. Melakukan analisa bug dan memastikan penyelesaian masalah secara tepat.\n10. Menyusun dokumentasi sistem, user guide, dan standar operasional fitur.\n11. Memantau implementasi fitur agar sesuai dengan spesifikasi dan timeline yang disepakati.\n12. Memberikan rekomendasi improvement berdasarkan analisis proses bisnis dan feedback pengguna.", "application_deadline": "2025-12-07", "quota": 1, "registered": 8, "position_type": "System Analyst", "government_agency": null, "sub_government_agency": null, "angkatan": "3", "tahun": "2025"}