{"id": 12475, "source_id": "a07cc241-fdc2-4604-b8ca-af89e94c29af", "company_name": "Eigerindo Multi Produk Industri", "province": "JAWA BARAT", "city": "KAB. BANDUNG", "recommended_degree": "Desain Media, Desain Komunikasi Visual, Desain Grafis, Desain Interior, Desain Produk (Sarjana, Diploma)", "job_title": "Graphic Design", "job_description": "1. Create visually appealing design for promotional materials, event visuals, social media graphics, and other creative assets.\n2. Develop visual content that promotes and reflects the company's brand\n3. Ensure that all designs adhere to EIGER’s brand guidelines, maintaining consistency across all marketing communication materials.\n4. Contribute to the brainstorming and conceptualization of creative ideas that align with EIGER’s brand identity and marketing goals.", "application_deadline": "2025-12-07", "quota": 3, "registered": 14, "position_type": "Graphic Design", "government_agency": null, "sub_government_agency": null, "angkatan": "3", "tahun": "2025"}