{"id": 13024, "source_id": "a07fe7cd-1a18-45eb-b21d-018dfba1f880", "company_name": "Yazid Mulia Property", "province": "JAWA TENGAH", "city": "KAB. TEGAL", "recommended_degree": "Teknik Informatika, Informatika, Sistem Informasi, Rekayasa Perangkat Lunak, Teknik Komputer (Diploma, Sarjana)", "job_title": "Staf IT", "job_description": "- Melakukan instalasi, konfigurasi, dan perawatan hardware & software.\n- Menangani troubleshooting jaringan, printer, komputer, dan perangkat kantor lainnya.\n- Memantau keamanan sistem dan memastikan data perusahaan terjaga.\n- Melakukan backup data berkala dan pemulihan apabila terjadi error.\n- Membantu pengembangan sistem internal serta kebutuhan IT harian.\n-Memberikan dukungan teknis kepada seluruh karyawan.", "application_deadline": "2025-12-07", "quota": 2, "registered": 3, "position_type": "Staf IT", "government_agency": null, "sub_government_agency": null, "angkatan": "3", "tahun": "2025"}