{"id": 13391, "source_id": "a07eb644-954e-45f3-b474-f08e5186678b", "company_name": "Herbatech Innopharma Industry", "province": "JAWA TENGAH", "city": "KAB. PURBALINGGA", "recommended_degree": "Analis Farmasi, Analis Farmasi Dan Makanan, Farmasi, Sains Dan Teknologi Farmasi, Farmasi Klinis (Sarjana, Diploma)", "job_title": "Research and Development", "job_description": "1. Fresh graduate atau berpengalaman  bidang R&D di industri OT, Komestik, & Pangan Olahan\n2. Memiliki pengetahuan terkait konsep pengembangan produk\n3. Memiliki pengetahuan di bidang pengujian laboratorium\n4. Memiliki pengetahuan tentang GMP, CPPOB, CPOTB dan Sistem Jaminan Produk Halal (SJPH)\n5. Mampu bekerja dalam tim maupun individu\n6. Disiplin, teliti, cekatan dan siap bekerja dengan target", "application_deadline": "2025-12-07", "quota": 1, "registered": 6, "position_type": "Research and Development", "government_agency": null, "sub_government_agency": null, "angkatan": "3", "tahun": "2025"}