{"id": 13855, "source_id": "a0805cfc-a65b-4385-8afa-29caa0924467", "company_name": "Belanja Pasti Indonesia", "province": "DAERAH ISTIMEWA YOGYAKARTA", "city": "KAB. KULON PROGO", "recommended_degree": "Manajemen, Ilmu Komunikasi, Pemasaran Digital, Psikologi (Diploma, Sarjana)", "job_title": "Digital Marketing", "job_description": "merancang dan menjalankan strategi pemasaran, mengelola kampanye iklan online (seperti di media sosial dan mesin pencari), mengoptimalkan situs web dengan SEO, membuat dan mengelola konten, menganalisis data untuk mengukur performa, serta mengelola hubungan dengan Key Opinion Leader (KOL) dan meningkatkan engagement pelanggan melalui kanal digital.", "application_deadline": "2025-12-07", "quota": 2, "registered": 2, "position_type": "Digital Marketing", "government_agency": null, "sub_government_agency": null, "angkatan": "3", "tahun": "2025"}