{"id": 13919, "source_id": "a0743a32-ec0d-4a79-be3b-48550534a6e4", "company_name": "Binokular Media Utama", "province": "DAERAH ISTIMEWA YOGYAKARTA", "city": "KAB. SLEMAN", "recommended_degree": "Ilmu Komunikasi, Statistika, Pendidikan Sosiologi, Ilmu Politik (Diploma, Sarjana)", "job_title": "Internship Data Support Socindex", "job_description": "Membantu koreksi sentimen percakapan warganet di media sosial, cleaning dan cek relevansi data medsos, serta pengecekan alert/konten negatif klien Socindex", "application_deadline": "2025-12-07", "quota": 2, "registered": 3, "position_type": "Internship Data Support Socindex", "government_agency": null, "sub_government_agency": null, "angkatan": "3", "tahun": "2025"}