{"id": 13922, "source_id": "a081702f-0194-4373-a13f-298c16972e62", "company_name": "Inamas Sintesis Teknologi", "province": "DAERAH ISTIMEWA YOGYAKARTA", "city": "KOTA YOGYAKARTA", "recommended_degree": "Teknik Industri, Logistik (Diploma, Sarjana)", "job_title": "Supply Chain", "job_description": "1. Memahami alur procurement, inventory control, warehouse, dan distribusi\n2. Mampu mengoperasikan Microsoft Excel, dan data reporting\n3. Bersedia melakukan koordinasi dengan vendor & pihak internal perusahaan\n4. Melakukan perencanaan kebutuhan material (material planning) berdasarkan forecast & kebutuhan produksi\n5. Melakukan analisis perputaran persediaan dan memastikan ketersediaan bahan tidak overstock/stockout", "application_deadline": "2025-12-07", "quota": 1, "registered": 3, "position_type": "Supply Chain", "government_agency": null, "sub_government_agency": null, "angkatan": "3", "tahun": "2025"}