{"id": 14009, "source_id": "a0805094-c8a4-41b2-bc15-33dc1fa39c94", "company_name": "Klick Express Mitra Grafika", "province": "DAERAH ISTIMEWA YOGYAKARTA", "city": "KOTA YOGYAKARTA", "recommended_degree": "Administrasi, Manajemen Bisnis, Manajemen, Administrasi Perkantoran, Manajemen Perkantoran (Diploma, Sarjana)", "job_title": "Admin Finance", "job_description": "-mencatat dan menghitung piutang konsumen\n-membuat & mengelola invoice\n-melakukan follow up tagihan\n-menerima & mengupdate pembayaran\n-arsip dokumen piutang\n-membuat laporan account receivable", "application_deadline": "2025-12-07", "quota": 1, "registered": 5, "position_type": "Admin Finance", "government_agency": null, "sub_government_agency": null, "angkatan": "3", "tahun": "2025"}