{"id": 14612, "source_id": "a080d17f-7d08-49b0-ae53-5ca4e4db6033", "company_name": "Air The Best Langga", "province": "JAWA TIMUR", "city": "KOTA MALANG", "recommended_degree": "Desain Grafis, Desain Komunikasi Visual, Ilmu Komunikasi, Komunikasi Digital dan Media (Sarjana)", "job_title": "Desainer Grafis", "job_description": "1. Membuat sketsa, rencana, prototipe dan konsep produk\n2. Menggunakan desain untuk menjawab kebutuhan pasar\n3. Memvisualisasikan ide dan pesan secara menarik\n4. Memastikan desain berfungsi dengan baik dan sesuai dengan tujuan penggunaan\n5. Melakukan koordinasi dengan manajemen\n6. Mampu mengelola media sosial", "application_deadline": "2025-12-07", "quota": 2, "registered": 5, "position_type": "Desainer Grafis", "government_agency": null, "sub_government_agency": null, "angkatan": "3", "tahun": "2025"}