{"id": 14819, "source_id": "a07ed0af-d00c-4da0-a6f2-be1330f6976a", "company_name": "Perumdam Maja Tirta", "province": "JAWA TIMUR", "city": "KOTA MOJOKERTO", "recommended_degree": "Akuntansi, Manajemen Bisnis (Sarjana, Diploma)", "job_title": "Bagian Keuangan", "job_description": "Bagian Keuangan bertugas untuk melakukan perbantuan dalam masalah pencatatan keuangan, pajak, layanan pelanggan dan tugas administrasi keuangan lainnya seperti penggajian dan pencatatan kas.", "application_deadline": "2025-12-07", "quota": 1, "registered": 7, "position_type": "Bagian Keuangan", "government_agency": null, "sub_government_agency": null, "angkatan": "3", "tahun": "2025"}