{"id": 14965, "source_id": "a07f0945-bd22-4c39-8385-c14df0056a50", "company_name": "Masjid Jami Nahdlatul Ulama Trawasan", "province": "JAWA TIMUR", "city": "KAB. JOMBANG", "recommended_degree": "Kebidanan (Diploma, Sarjana)", "job_title": "bidan", "job_description": "melakukan emeriksaan dasar maternal pada pasienwanita pada umumnya. melakukan therapy dan tindakan - tindaan kebidanan sesuai kopetensi yang di miliki", "application_deadline": "2025-12-07", "quota": 2, "registered": 9, "position_type": "bidan", "government_agency": null, "sub_government_agency": null, "angkatan": "3", "tahun": "2025"}