{"id": 1528, "source_id": "a06ec15d-b5ea-4934-8c58-268f44f3c8ca", "company_name": "PT Awal Bros Sehat Sentosa", "province": "RIAU", "city": "KAB. ROKAN HILIR", "recommended_degree": "Fisioterapi (Sarjana)", "job_title": "Fisioterapi", "job_description": "- Melakukan anamnesis (wawancara), pemeriksaan fisik, dan diagnosis fisioterapi untuk mengidentifikasi masalah gerak dan fungsi tubuh pasien. \n- Membantu pasien untuk memulihkan, mempertahankan, dan memaksimalkan mobilitas, fungsi, dan kesejahteraan mereka\n- Mengelola dan mengurangi rasa sakit akut maupun kronis melalui teknik-teknik fisioterapi. \n- Memberikan edukasi kepada pasien dan keluarganya tentang kondisi mereka, tindakan yang akan dijalani, serta memberikan saran mengenai gaya hidup, postur yang benar, dan cara mengangkat beban secara aman untuk mencegah cedera", "application_deadline": "2025-12-07", "quota": 2, "registered": 4, "position_type": "Fisioterapi", "government_agency": null, "sub_government_agency": null, "angkatan": "3", "tahun": "2025"}