{"id": 16260, "source_id": "a07905fc-4080-474d-811d-88b9635235d9", "company_name": "Meares Soputan Mining", "province": "SULAWESI UTARA", "city": "KAB. MINAHASA UTARA", "recommended_degree": "Manajemen, Manajemen Administrasi, Manajemen Sumber Daya Manusia, Akuntansi (Diploma, Sarjana)", "job_title": "Magang Administrasi Human Capital", "job_description": "* Sarjana Manajemen Sumber Daya Manusia, Manajemen atau Akuntansi\n* Memahami dasar-dasar siklus karyawan (mulai dari rekrutmen hingga offboarding). Mampu mengelola file/dokumen kepegawaian secara rapi dan terarsip dengan baik.\n* Mampu menggunakan fungsi-fungsi dasar hingga menengah Excel (VLOOKUP, Pivot Table, formula matematis) untuk tracking data kehadiran, timesheet, dan payroll sederhana\nPenempatan di Site Tokatindung, Minahasa Utara", "application_deadline": "2025-12-07", "quota": 1, "registered": 16, "position_type": "Magang Administrasi Human Capital", "government_agency": null, "sub_government_agency": null, "angkatan": "3", "tahun": "2025"}