{"id": 16449, "source_id": "a081116d-1697-4466-b653-1d00cf9923f9", "company_name": "BPVP Bantaeng", "province": "SULAWESI SELATAN", "city": "KAB. BANTAENG", "recommended_degree": "Pendidikan Luar Biasa, Manajemen Pemasaran Untuk Warga Negara Berkebutuhan Khusus, Pendidikan Khusus (Diploma, Sarjana)", "job_title": "Juru Bahasa Isyarat", "job_description": "1.Menerjemahkan Bahasa Lisan ke Bahasa Isyarat\n2.Mendukung aksesibilitas bagi penyandang disabilitas rungu    \n\n\n#terbuka untuk semua jurusan (selama memiliki kompetensi penguasaan bahasa isyarat)", "application_deadline": "2025-12-07", "quota": 1, "registered": 3, "position_type": "Juru Bahasa Isyarat", "government_agency": "Kementerian Ketenagakerjaan", "sub_government_agency": "BPVP Bantaeng", "angkatan": "3", "tahun": "2025"}