{"id": 16815, "source_id": "a07c2eec-7599-4d39-9bf3-8ffaa6b91a4b", "company_name": "PT Suracojaya Abadimotor", "province": "SULAWESI SELATAN", "city": "KOTA MAKASSAR", "recommended_degree": "Psikologi, Hukum, Administrasi Perkantoran (Sarjana)", "job_title": "Staff HRD", "job_description": "-  input data karyawan by Sistem\n-  ikut dalam seleksi/interview karyawan\n-  filing data/dokumen\n-  membantu tugas lain HRD \n-  membantu team Trainer dalam hal sebelum, selama dan setelah aktivitas Training", "application_deadline": "2025-12-07", "quota": 1, "registered": 18, "position_type": "Staff HRD", "government_agency": null, "sub_government_agency": null, "angkatan": "3", "tahun": "2025"}