{"id": 16914, "source_id": "a07eb3d9-4110-4bc9-8240-16afc520786c", "company_name": "Bosowa Berlian Motor", "province": "SULAWESI SELATAN", "city": "KOTA MAKASSAR", "recommended_degree": "Administrasi, Psikologi, Hukum, Sistem Informasi, Statistik (Sarjana)", "job_title": "Human Capital & Legal Intern", "job_description": "benefit: Mengelola gaji, tunjangan, dan benefit lainnya untuk memastikan keseimbangan dan menjaga kepuasan karyawan.\nRetensi karyawan: Menerapkan strategi untuk meminimalkan turnover karyawan dengan cara memberikan apresiasi, pelatihan karier, dan mengatasi masalah di lingkungan kerja.\nManajemen data dan administrasi: Mengurus database karyawan, data kehadiran, cuti, BPJS, kontrak kerja, dan administrasi SDM lainnya.\nPeran sebagai agen perubahan: Membantu organisasi mengelola perubahan dan mengintegrasikan teknologi baru dalam proses manajemen SDM.", "application_deadline": "2025-12-07", "quota": 3, "registered": 46, "position_type": "Human Capital & Legal Intern", "government_agency": null, "sub_government_agency": null, "angkatan": "3", "tahun": "2025"}