{"id": 17070, "source_id": "a0805a0f-6382-4489-9c27-16d44255dbb9", "company_name": "BPS Kabupaten Bone Bolango", "province": "GORONTALO", "city": "KAB. BONE BOLANGO", "recommended_degree": "Teknologi Informasi, Manajemen, Ekonomi, Akuntansi (Diploma, Sarjana)", "job_title": "Asisten Pengelola Keuangan", "job_description": "Membantu proses pengelolaan administrasi keuangan, termasuk pencatatan transaksi, verifikasi dokumen pendukung, penyusunan laporan keuangan, serta memastikan kepatuhan pada aturan pengelolaan anggaran.", "application_deadline": "2025-12-07", "quota": 1, "registered": 17, "position_type": "Asisten Pengelola Keuangan", "government_agency": "Badan Pusat Statistik", "sub_government_agency": "BPS Kabupaten Bone Bolango", "angkatan": "3", "tahun": "2025"}