{"id": 19171, "source_id": "a077a1aa-8656-4d1a-b8fb-23ba86e4c669", "company_name": "Wahyu Abadi Indomedia", "province": "DKI JAKARTA", "city": "KOTA ADM. JAKARTA SELATAN", "recommended_degree": "Film dan Televisi, Teknik Multimedia, Manajemen & Produksi Film Video & TV, Akuntansi, Akuntansi Manajemen (Sarjana)", "job_title": "Magang Editing & Pascaproduksi", "job_description": "Mengolah dan menyunting video untuk kebutuhan konten digital, iklan, dan dokumentasi. Bertugas memastikan kualitas audio-visual optimal, color grading dasar, hingga penambahan elemen grafis.", "application_deadline": "2025-12-07", "quota": 5, "registered": 16, "position_type": "Magang Editing & Pascaproduksi", "government_agency": null, "sub_government_agency": null, "angkatan": "3", "tahun": "2025"}