{"id": 20969, "source_id": "a08108cf-a913-4762-98f3-40ab039956c3", "company_name": "PT. Amerta Indah Otsuka", "province": "DKI JAKARTA", "city": "KOTA ADM. JAKARTA SELATAN", "recommended_degree": "Ilmu Teknologi Pangan, Ilmu dan Teknologi Pangan, Teknologi Pangan, Ilmu Gizi, Gizi (Diploma, Sarjana)", "job_title": "Resarch & Development Intern", "job_description": "Collecting market survey data on Soyjoy’s texture to helps brands understand consumer preferences and guide better product improvement and innovation.", "application_deadline": "2025-12-07", "quota": 1, "registered": 77, "position_type": "Resarch & Development Intern", "government_agency": null, "sub_government_agency": null, "angkatan": "3", "tahun": "2025"}