{"id": 21358, "source_id": "a080cdba-4769-4676-ac46-e088221eb1de", "company_name": "Sarandi Karya Nugraha", "province": "JAWA BARAT", "city": "KAB. SUKABUMI", "recommended_degree": "Teknik Manajemen Industri, PJJ Teknik Industri, Elektro Mekanika, Manajemen Informatika, Mesin Industri (Sarjana)", "job_title": "Staf Sistem dan Legal", "job_description": "Merencanakan dan memantau program audit internal, 2.2.\tMenyusun  pedoman  manajemen  yang  disahkan  oleh  Direksi  yang berkaitan di perusahaan,  Merencanakan  dan   melaksanakan  program  terkait   tentang   Sistem Manajemen Mutu diperusahaan, Mengidentifikasikan dan mengelola program-program untuk perbaikan sistem manajemen, 3. 3.\tMenentukan  apakah  kebijaksanaan  dan  praktik  yang  diajukan  telah memenuhi persyaratan ISO, 3. 10.\tMerencanakan  dan   melaksanakan  program  terkait   tentang   Sistem Manajemen Mutu diperusahaan", "application_deadline": "2025-12-07", "quota": 1, "registered": 9, "position_type": "Staf Sistem dan Legal", "government_agency": null, "sub_government_agency": null, "angkatan": "3", "tahun": "2025"}