{"id": 22632, "source_id": "a080c47d-ca8d-4025-95a6-ab1b414b296e", "company_name": "PT. Bank Tabungan Negara (Persero) Tbk. Kantor Cabang Syariah Bandung", "province": "JAWA BARAT", "city": "KOTA BANDUNG", "recommended_degree": "Administrasi, Administrasi Bisnis, Ekonomi, Manajemen (Sarjana)", "job_title": "General Support", "job_description": "Membantu proses administrasi pada bagian logistik dan human capital, sesuai ketentuan perbankan.\nTugas dan tanggung jawab :\n1. Melakukan administrasi pengadaan\n2. Melakukan administrasi dan rekapitulasi pengeluaran operasional\n3. Melakukan rekonsiliasi antara pengeluaran dengan anggaran", "application_deadline": "2025-12-07", "quota": 1, "registered": 26, "position_type": "General Support", "government_agency": null, "sub_government_agency": null, "angkatan": "3", "tahun": "2025"}