{"id": 23102, "source_id": "a080362e-1274-41eb-87b3-0d77b1d0f4f6", "company_name": "BPS Kabupaten Karawang", "province": "JAWA BARAT", "city": "KAB. KARAWANG", "recommended_degree": "Ekonomi, Manajemen, Teknologi Informasi, Administrasi, Akuntansi (Diploma, Sarjana)", "job_title": "Asisten Pengelola Keuangan", "job_description": "Membantu proses pengelolaan administrasi keuangan, termasuk pencatatan transaksi, verifikasi dokumen pendukung, penyusunan laporan keuangan, serta memastikan kepatuhan pada aturan pengelolaan anggaran.", "application_deadline": "2025-12-07", "quota": 2, "registered": 54, "position_type": "Asisten Pengelola Keuangan", "government_agency": "Badan Pusat Statistik", "sub_government_agency": "BPS Kabupaten Karawang", "angkatan": "3", "tahun": "2025"}