{"id": 23295, "source_id": "a07e3f52-9e6d-442c-96d5-07e8552cb06e", "company_name": "Kalam Inti Sentosa", "province": "JAWA TENGAH", "city": "KAB. TEGAL", "recommended_degree": "Desain Produk Kayu Dan Serat, Rekayasa Kayu, Arsitektur Interior, Desain Interior, Kehutanan (Diploma, Sarjana)", "job_title": "Kria Kayu", "job_description": "-Membuat, memotong, membentuk, dan merakit produk berbahan kayu sesuai desain.\n- Mengoperasikan peralatan perkayuan (gergaji, mesin serut, bor, router, dll).\n- Melakukan finishing seperti pengamplasan, coating, pelitur, dan pengecatan.\n- Membaca desain, sketsa, atau ukuran kerja dari tim desain/arsitek.\n- Melakukan quality control untuk memastikan hasil produk rapi dan sesuai standar.\n- Merawat dan menjaga kebersihan alat serta area kerja.", "application_deadline": "2025-12-07", "quota": 2, "registered": 5, "position_type": "Kria Kayu", "government_agency": null, "sub_government_agency": null, "angkatan": "3", "tahun": "2025"}