{"id": 23342, "source_id": "a0761f8d-7206-4c45-8bc9-b4b6ccfb23f1", "company_name": "Rumah Sakit Islam Kendal", "province": "JAWA TENGAH", "city": "KAB. KENDAL", "recommended_degree": "Okupasi Terapi, Terapi Okupasi (Diploma)", "job_title": "OKUPASI TERAPI", "job_description": "Okupasi terapi/Lulusan D3 Okupasi Terapi\nObservasi dan asesmen dasar\nMengamati kemampuan anak dalam aktivitas sehari-hari (ADL: makan, berpakaian, bermain, belajar).\nMembantu pengukuran keterampilan motorik halus, koordinasi tangan-mata, atensi, dan kemampuan sosial.\nMengisi lembar observasi perkembangan di bawah bimbingan supervisor.\nPerencanaan dan pelaksanaan terapi\n\nMembantu menyusun dan menyiapkan media terapi (alat permainan edukatif, sensory tools, papan aktivitas).\nMendampingi anak selama sesi terapi di bawah supervisi terapis utama.\nMelatih anak dalam kegiatan motorik halus (menulis, menggenggam, memotong, meronce), motorik kasar ringan, serta permainan sensori.\n\nMengajarkan strategi kompensasi dan adaptasi sederhana bagi anak yang memiliki hambatan tertentu (misal autisme, ADHD, cerebral palsy, down syndrome).\nDokumentasi dan evaluasi\n\nMencatat hasil terapi harian (observasi perilaku, respons anak, kemajuan aktivitas).\n\nMembantu menyusun laporan perkembangan anak secara periodik.\nMenyampaikan laporan kepada pembimbing / orang tua (di bawah supervisi).\nEdukasi & kolaborasi\nMembantu kegiatan edukasi orang tua terkait stimulasi di rumah.", "application_deadline": "2025-12-07", "quota": 2, "registered": 6, "position_type": "OKUPASI TERAPI", "government_agency": null, "sub_government_agency": null, "angkatan": "3", "tahun": "2025"}