{"id": 23494, "source_id": "a07e56b3-c31f-4a2c-8aa0-9063aa77de04", "company_name": "Konimex", "province": "JAWA TENGAH", "city": "KAB. SUKOHARJO", "recommended_degree": "Elektronika, Mekatronika (Diploma)", "job_title": "Electro Technician", "job_description": "1. Melakukan perbaikan komponen elektrik\n2. Membuat design rangkaian elektrik dan kontrol sederhana\n3. Melakukan analisa dan evaluasi preventive maintenance sistem kelistrikan\n4. Melakukan trouble shooting rangkaian kontrol sederhana\n5. Melakukan instalasi listrik 3 phase, jaringan telepon, fire alarm, sound system\n6. Melaksanakan 5R", "application_deadline": "2025-12-07", "quota": 1, "registered": 9, "position_type": "Electro Technician", "government_agency": null, "sub_government_agency": null, "angkatan": "3", "tahun": "2025"}