{"id": 23732, "source_id": "a0745a97-77cc-46d0-a223-b1222fd58957", "company_name": "PT. Batang Alum Industries", "province": "JAWA TENGAH", "city": "KAB. BATANG", "recommended_degree": "Teknik Sipil, Teknik Sipil Bangunan Gedung, Teknik Sipil dan Lingkungan (Sarjana)", "job_title": "Teknisi Teknik Sipil", "job_description": "1. Menangani pemeliharaan dan perbaikan bangunan pabrik, kantor dan mess perusahaan.\n2. Membuat RAB.  \n3. Memantau  ketersediaan  tenaga  Teknisi Bangunan baik dalam hal kuantitas maupun kualitas sesuai  standar  ditetapkan sehingga tidak menghambat proses perbaikan.\n4. Memantau  dan  mengatur  schedule  pengajuan permintaan perbaikan dari tiap departemen. \n5. Menjaga kualitas hasil perbaikan yang dilakukan oleh Teknisi Bagian Bangunan.", "application_deadline": "2025-12-07", "quota": 1, "registered": 17, "position_type": "Teknisi Teknik Sipil", "government_agency": null, "sub_government_agency": null, "angkatan": "3", "tahun": "2025"}