{"id": 2375, "source_id": "a076907a-ab38-454b-98c8-19220ace7a6d", "company_name": "PT. Graha Bernoza", "province": "BENGKULU", "city": "KOTA BENGKULU", "recommended_degree": "Kesehatan Lingkungan (Diploma)", "job_title": "Kesling", "job_description": "1. Memantau kualitas air bersih, udara, dan kebersihan umum\n2. Mengawasi kebersihan dan sanitasi tempat-tempat umum, termasuk fasilitas makan dan sarana penunjang lainnya. \n3. Memastikan semua aspek lingkungan rumah sakit memenuhi standar dan persyaratan kesehatan. \n4. Melakukan pemeriksaan dan tindakan hygiene sanitasi pada tempat pengolahan makanan\n5. Mengelola limbah medis dan non-medis, mulai dari pemilahan, pengumpulan, hingga pemusnahannya.", "application_deadline": "2025-12-07", "quota": 1, "registered": 20, "position_type": "Kesling", "government_agency": null, "sub_government_agency": null, "angkatan": "3", "tahun": "2025"}