{"id": 2391, "source_id": "a072b03b-7118-4198-9b30-e9ca11dcf743", "company_name": "KANIM KELAS I TPI BENGKULU", "province": "BENGKULU", "city": "KOTA BENGKULU", "recommended_degree": "Desain Komunikasi Visual, Ilmu Komunikasi (Sarjana)", "job_title": "Pengelola Kehumasan", "job_description": "1. Menyusun materi layanan informasi untuk media elektronik\n2. Menyusun berita pelayanan informasi dan kehumasan melalui media cetak, elektronik dan daring (online)\n3. Menyusun naskah pelayanan informasi dan kehumasan dalam bentuk: ceramah, pidato, dan bahan tayang\n4. Menyelenggarakan penerbitan materi pelayanan informasi untuk media cetak, elektronik, dan daring (online)\n5. Melaksanakan tugas peliputan kegiatan kelembagaan dalam bentuk foto dan video", "application_deadline": "2025-12-07", "quota": 1, "registered": 27, "position_type": "Pengelola Kehumasan", "government_agency": "Kementerian Imigrasi dan Pemasyarakatan", "sub_government_agency": "KANIM KELAS I TPI BENGKULU", "angkatan": "3", "tahun": "2025"}