{"id": 2416, "source_id": "a07888b5-bc6e-4889-b7ec-7e5556f8ac55", "company_name": "Great Giant Pineapple", "province": "LAMPUNG", "city": "KAB. LAMPUNG TENGAH", "recommended_degree": "Akuntansi (Sarjana)", "job_title": "Finance Controller Plantation - Internship", "job_description": "Cost controll for all commodity in plantation Consold commodity all plantation Control & monitoring Inventory & rental activity in plantation", "application_deadline": "2025-12-07", "quota": 1, "registered": 3, "position_type": "Finance Controller Plantation - Internship", "government_agency": null, "sub_government_agency": null, "angkatan": "3", "tahun": "2025"}