{"id": 24273, "source_id": "a080c48d-91a4-4911-98e2-81ce8680e12f", "company_name": "Muhammad Firdan Ashari", "province": "DAERAH ISTIMEWA YOGYAKARTA", "city": "KAB. BANTUL", "recommended_degree": "Desain Produk (Sarjana)", "job_title": "Desainer Produk", "job_description": "1. Membuat konsep desain produk dekorasi rumah.\n2. Melakukan riset tren desain, referensi pasar, dan kebutuhan pelanggan.\n3. Membuat sketsa, layout, dan final artwork (AI/PS/Corel) siap produksi.\n4. Menyusun file CNC/laser-cut (vector cutting) sesuai standar produksi ERGOO.\n5. Bekerja sama dengan tim produksi untuk memastikan desain dapat diproduksi dengan baik.\n6. Melakukan revisi desain sesuai masukan tim atau umpan balik pelanggan.\n7. Membuat mockup produk untuk kebutuhan marketplace dan media sosial.\n8. Mengelola database desain (naming, SKU, folder per kategori).", "application_deadline": "2025-12-07", "quota": 1, "registered": 5, "position_type": "Desainer Produk", "government_agency": null, "sub_government_agency": null, "angkatan": "3", "tahun": "2025"}