{"id": 2460, "source_id": "a080b2be-e837-41b3-843f-f826b4077bcb", "company_name": "Bank Perekonomian Rakyat Syariah Mitra Agro Usaha", "province": "LAMPUNG", "city": "KOTA BANDAR LAMPUNG", "recommended_degree": "Hukum Ekonomi Syariah, Ekonomi Syariah (Sarjana, Diploma)", "job_title": "Funding Officer", "job_description": "Melakukan pemasaran produk dana seperti tabungan, deposito, dan produk simpanan lainnya.\n\nMencari dan membangun hubungan dengan calon nasabah perorangan maupun institusi.\n\nMelakukan canvassing, kunjungan lapangan, dan presentasi untuk memperoleh dana pihak ketiga.\n\nMenjaga serta meningkatkan hubungan dengan nasabah existing untuk menjaga loyalitas dan mempertahankan dana.\n\nMengidentifikasi kebutuhan nasabah dan menawarkan produk yang sesuai secara tepat.\n\nMengumpulkan dan memastikan kelengkapan dokumen pembukaan rekening atau produk dana.\n\nBerkoordinasi dengan tim operasional terkait proses pembukaan rekening dan administrasi nasabah.\n\nMencapai target penghimpunan dana yang telah ditetapkan perusahaan.\n\nMelakukan follow-up berkala kepada nasabah untuk memastikan layanan tetap optimal.", "application_deadline": "2025-12-07", "quota": 1, "registered": 4, "position_type": "Funding Officer", "government_agency": null, "sub_government_agency": null, "angkatan": "3", "tahun": "2025"}