{"id": 2545, "source_id": "a080db6c-1b19-41fb-814d-b069ccc9247a", "company_name": "Tdm Gading Rejo", "province": "LAMPUNG", "city": "KAB. PRINGSEWU", "recommended_degree": "Ilmu Administrasi Negara, Ilmu Administrasi Negara, Ilmu Administrasi Niaga, Ilmu Aktuaria, Pendidikan Bahasa Inggris (Diploma, Sarjana)", "job_title": "ADMINISTRASI STAFF", "job_description": "ADMIN DO PENJUALAN UNIT DAN ADMIN STNK BPKB\n\nINPUT DO PENJUALAN\nCEK UNIT AGING\nCEK KSU\nSO UNIT DAN KSU\n\nSTNK/BPKB:\nMELAYANIN PELANGGAN\nBELAJAR FLP\nINPUT STNK\nINPUT BPKB\nCEK AGING STNK DAN BPKB", "application_deadline": "2025-12-07", "quota": 1, "registered": 12, "position_type": "ADMINISTRASI STAFF", "government_agency": null, "sub_government_agency": null, "angkatan": "3", "tahun": "2025"}