{"id": 27721, "source_id": "a07e363d-c8cd-45c4-a232-72a3ead77888", "company_name": "PT.manakarra Unggul Lestari", "province": "SULAWESI BARAT", "city": "KAB. MAMUJU", "recommended_degree": "Teknik Mesin, Teknik Sipil, Agroteknologi, Manajemen, Teknik Geologi (Diploma, Sarjana)", "job_title": "Agroindustri Trainee Staff", "job_description": "Posisi Trainee Staff di Divisi Agroindustri merupakan jabatan strategis yang dirancang bagi individu berdedikasi yang siap terjun langsung ke dalam operasional inti bisnis pertanian dan indutsri kelapa sawit. Melalui program pelatihan terstruktur, kandidat terpilih akan mendapatkan eksposur mendalam terhadap seluruh rantai nilai agroindustri, mulai dari manajemen perkebunan/pasokan bahan mentah, proses produksi di pabrik, hingga penjaminan mutu produk akhir. Tanggung jawab utama peran ini mencakup dukungan aktif terhadap kegiatan harian supervisor dalam perencanaan operasional, pengumpulan dan analisis data efisiensi produksi, serta memastikan kepatuhan ketat terhadap  prosedur operasi standar (SOP). Dibutuhkan lulusan baru yang dinamis dari latar belakang pendidikan relevan seperti Teknis Sipil, Teknik Mesin, Agroteknologi, Agribisnis, dan jurusan lainnta yang berkaitan yang memiliki kemampuan analitis kuat, etos kerja tinggi, dan kesiapan untuk beradaptasi di lingkungan operasional yang menuntut, dengan tujuan akhir menjadi staf penuh yang kompeten.", "application_deadline": "2025-12-07", "quota": 10, "registered": 122, "position_type": "Agroindustri Trainee Staff", "government_agency": null, "sub_government_agency": null, "angkatan": "3", "tahun": "2025"}