{"id": 2799, "source_id": "a078b8fb-9d67-4fda-a5c3-99fddb7c3661", "company_name": "Kantor Bahasa Provinsi Kepulauan Riau", "province": "KEPULAUAN RIAU", "city": "KAB. BINTAN", "recommended_degree": "Bahasa dan Sastra Indonesia, Sastra Indonesia, Pendidikan Bahasa Dan Sastra Indonesia, Pendidikan Bahasa dan Sastra Indonesia, Pendidikan Bahasa, Sastra Indonesia dan Daerah (Sarjana)", "job_title": "Perevitalisasi Bahasa dan Sastra", "job_description": "Pelestarian, revitalisasi, dan pemberdayaan bahasa dan sastra daerah melalui penyusunan model revitalisasi, fasilitasi komunitas, serta pengembangan bahan ajar dan media pelestarian bahasa dan sastra", "application_deadline": "2025-12-07", "quota": 1, "registered": 4, "position_type": "Perevitalisasi Bahasa dan Sastra", "government_agency": "Kementerian Pendidikan Dasar dan Menengah", "sub_government_agency": "Kantor Bahasa Provinsi Kepulauan Riau", "angkatan": "3", "tahun": "2025"}