{"id": 3676, "source_id": "a07cb7ad-5c15-4e90-b197-5a9f0e72be48", "company_name": "Herba Penawar Alwahida Indonesia", "province": "DKI JAKARTA", "city": "KOTA ADM. JAKARTA TIMUR", "recommended_degree": "Manajemen Pemasaran/Marketing, Ilmu Komunikasi, Komunikasi (Diploma, Sarjana)", "job_title": "Social Media Specialist (Product Branding)", "job_description": "- Perencanaan dan Strategi: Merencanakan, membuat, dan mengelola kampanye konten pemasaran untuk mencapai tujuan bisnis.\n- Pembuatan Konten: Membuat brief untuk mengoptimalkan konten yang menarik dalam berbagai jenis konten (Video, grafis, artikel dll)\n- Riset dan Analisis: Melakukan riset tren terbaru dan memahami audiens target.\n- Kolaborasi Tim: Bekerja sama dengan tim lain untuk menyelaraskan strategi dan mencapai tujuan bersama.", "application_deadline": "2025-12-07", "quota": 1, "registered": 3, "position_type": "Social Media Specialist (Product Branding)", "government_agency": null, "sub_government_agency": null, "angkatan": "3", "tahun": "2025"}