{"id": 4777, "source_id": "a07eb6f7-4ccc-416e-a943-28774bc10d0b", "company_name": "Perusahaan Perseroan (Persero) PT. Bahana Pembinaan Usaha Indonesia", "province": "DKI JAKARTA", "city": "KOTA ADM. JAKARTA SELATAN", "recommended_degree": "Akuntansi (Sarjana)", "job_title": "Manajemen Aset", "job_description": "1. Melakukan rekonsiliasi antara data hasil stock opname dan data pencatatan akuntansi. \n2. Meregistrasi aset IFG di ERP (Oracle) berdasarkan hasil opname fisik dan/atau data dari dokumen pendukung.\n3.Membantu pelaksanaan tugas-tugas ad-hoc lainnya.", "application_deadline": "2025-12-07", "quota": 2, "registered": 5, "position_type": "Manajemen Aset", "government_agency": null, "sub_government_agency": null, "angkatan": "3", "tahun": "2025"}