{"id": 481, "source_id": "a0703377-b63f-4260-b1ce-d26e972874dc", "company_name": "PT Sinergi Mutiara Cemerlang", "province": "SULAWESI SELATAN", "city": "KOTA MAKASSAR", "recommended_degree": "Teknik Sipil, Teknik Sipil Infrastruktur Perkotaan, Teknik Infrastruktur Lingkungan, Teknik Infrastruktur Sipil dan Perancangan Arsitektur, Arsitektur (Diploma, Sarjana)", "job_title": "Internship - Infrastucture Inspector", "job_description": "- Mendampingi tim dalam pengawasan harian pembangunan (jalan, drainase, bangunan fasilitas, utilitas, dan proyek infrastruktur lainnya).\n- Melakukan cek progres pekerjaan di lapangan dan mencatat perkembangan setiap hari.\n- Mendokumentasikan pekerjaan dengan foto, video, dan catatan teknis.\n- Membantu melakukan quality check terhadap material dan hasil pekerjaan sesuai spesifikasi.\n- Membantu mengecek kesesuaian pekerjaan dengan shop drawing atau gambar kerja.\n- Menyusun dan memperbarui laporan harian (daily report) dan data progres.\n- Mendampingi tim dalam koordinasi dengan kontraktor dan memastikan pekerjaan sesuai standar keselamatan (K3).\n- Membantu melakukan pengukuran sederhana di lapangan (dimensi, elevasi, volume).", "application_deadline": "2025-12-07", "quota": 2, "registered": 8, "position_type": "Internship - Infrastucture Inspector", "government_agency": null, "sub_government_agency": null, "angkatan": "3", "tahun": "2025"}