{"id": 5067, "source_id": "a074a7cb-bf1e-4deb-b717-229c416a45a6", "company_name": "Sentra Sejahtera Utama", "province": "DKI JAKARTA", "city": "KOTA ADM. JAKARTA SELATAN", "recommended_degree": "Desain Komunikasi Visual, Hubungan Masyarakat dan Komunikasi Digital (Sarjana)", "job_title": "Content & Social Media", "job_description": "1. Pembuatan Konten\nMembantu membuat konten harian: caption, poster, carousel, short video, dan infografis.\nMelakukan riset tren konten, topik relevan, dan ide kreatif.\nEditing foto/video dasar untuk kebutuhan sosial media.\n\n2. Administrasi & Manajemen Konten\nMembantu menyusun dan menjalankan kalender konten.\nMengorganisir file visual (foto, video, desain) agar rapi dan mudah dicari.\n\n3. Kolaborasi Tim\nBekerja sama dengan tim marketing, desain, dan brand untuk menyelaraskan strategi konten.\nMendukung kebutuhan konten untuk campaign, event, atau produk baru.", "application_deadline": "2025-12-07", "quota": 1, "registered": 5, "position_type": "Content & Social Media", "government_agency": null, "sub_government_agency": null, "angkatan": "3", "tahun": "2025"}