{"id": 6218, "source_id": "a08169eb-b990-4b0a-995b-9f9d0056924b", "company_name": "Kazeer Solusi Digital", "province": "DKI JAKARTA", "city": "KOTA ADM. JAKARTA SELATAN", "recommended_degree": "Manajemen, Akuntansi, Matematika, Biologi, Ilmu Perikanan (Diploma, Sarjana)", "job_title": "Admin Operasional", "job_description": "Admin Operasional di Kazeer bertugas memastikan seluruh proses operasional perusahaan berjalan lancar, tertata, dan efisien untuk mendukung aktivitas tim serta layanan kepada pengguna. Tugasnya meliputi mengelola data administrasi, memantau pesanan bundling perangkat kasir, mengatur pengiriman dan stok perangkat, mencatat kebutuhan internal, serta memastikan seluruh dokumentasi operasional tersimpan rapi. Admin Operasional juga berkoordinasi dengan tim customer support, marketing, dan finance untuk memastikan setiap permintaan atau laporan dapat ditindaklanjuti dengan cepat. Selain itu, peran ini mencakup pemantauan jadwal, pengaturan rapat internal, dan pembaruan status pekerjaan agar alur operasional di Kazeer tetap berjalan teratur dan mendukung pertumbuhan perusahaan.", "application_deadline": "2025-12-07", "quota": 4, "registered": 11, "position_type": "Admin Operasional", "government_agency": null, "sub_government_agency": null, "angkatan": "3", "tahun": "2025"}