{"id": 6369, "source_id": "a07f6687-41e6-43e3-a5e3-0dbf87c7fc5a", "company_name": "BPJS KETENAGAKERJAAN", "province": "DKI JAKARTA", "city": "KOTA ADM. JAKARTA SELATAN", "recommended_degree": "Hukum (Sarjana)", "job_title": "Hukum Kelembagaan Intern", "job_description": "1. Melakukan pendataan dan pengarsipan dokumen produk hukum internal, surat edaran, serta dokumen terkait kepatuhan regulasi (regulatory compliance) sesuai ketentuan yang berlaku.\n2. Membantu proses penataan, pemeliharaan, dan pembaruan database dokumen agar tertib dan mudah ditelusuri.\n3. Mendukung kebutuhan administratif terkait permintaan salinan atau informasi dasar dokumen dari unit kerja terkait.\n4.  Penempatan: DEPUTI BIDANG KEPATUHAN & HUKUM (Jakarta)\n5. Magang dilakukan secara OFFLINE Senin-Jumat Pukul 08.00 - 17.00", "application_deadline": "2025-12-07", "quota": 2, "registered": 14, "position_type": "Hukum Kelembagaan Intern", "government_agency": "BPJS KETENAGAKERJAAN", "sub_government_agency": null, "angkatan": "3", "tahun": "2025"}