{"id": 6399, "source_id": "a074d38a-b75b-4bea-9fbc-d7bb1f2c74fd", "company_name": "Millenio Amerta Data", "province": "DKI JAKARTA", "city": "KOTA ADM. JAKARTA PUSAT", "recommended_degree": "Ilmu Komputer, Sistem informasi, Teknik informatika (Sarjana, Diploma)", "job_title": "Quality Assurance Engineer (QA)", "job_description": "Lokasi: On site (WFO)\nStatus: Magang (Full-time)\nDurasi: 6 bulan\nHari Kerja/Waktu : Senin-Jumat/09.00 - 18.00\n\nDeskripsi Pekerjaan\nSebagai QA Intern, Anda akan mendukung tim QA dalam memastikan kualitas dan keandalan aplikasi sebelum dirilis.\nTanggung jawab utama Anda meliputi:\n•\tMembuat dan menjalankan test case berdasarkan kebutuhan sistem.\n•\tMelakukan pengujian manual (fungsional, regresi, dan UI/UX).\n•\tMembantu pelaporan dan pelacakan bug menggunakan tools seperti Jira atau Trello.\n•\tMendukung dokumentasi pengujian dan pelaporan hasil pengujian.\n•\t(Opsional) Membantu membuat skrip otomatis sederhana jika memiliki keterampilan dasar dalam pengujian otomatis.\nPersyaratan\n•\tFreshgraduate Lulusan S1/D4/D3, dari jurusan Ilmu Komputer, Sistem Informasi, Teknik Informatika, atau bidang terkait\n•\tMemahami dasar-dasar Software Testing Life Cycle (STLC) dan Software Development Life Cycle (SDLC).\n•\tTeliti, komunikatif, dan mampu bekerja secara mandiri maupun dalam tim.\n•\tFamiliar dengan tools berikut:\no\tJIRA / Trello (pelacakan bug)\no\tPostman (pengujian API)\no\tExcel / Google Sheets (dokumentasi pengujian)\n•\t(Diutamakan) Pengetahuan dasar tentang Automation Testing (misalnya Selenium, Katalon, Cypress, atau JMeter).\n•\tBersedia berkomitmen untuk magang minimal 6 bulan.\n•\tWajib hadir daily sync meeting dengan tim setiap hari kerja pukul 10.00-10.30 atau 10.30-11.00", "application_deadline": "2025-12-07", "quota": 3, "registered": 15, "position_type": "Quality Assurance Engineer (QA)", "government_agency": null, "sub_government_agency": null, "angkatan": "3", "tahun": "2025"}