{"id": 6422, "source_id": "a07d2d4f-afdc-4660-b711-f47d5170cfbd", "company_name": "Mithra Yasa Satria", "province": "DKI JAKARTA", "city": "KOTA ADM. JAKARTA SELATAN", "recommended_degree": "Manajemen, Ilmu Hukum, Ilmu Pendidikan Agama Islam, Administrasi Publik, Tadris Bahasa Indonesia (Sarjana)", "job_title": "Divisi Humas", "job_description": "Divisi Humas merupakan unit strategis yang bertanggung jawab membangun, memelihara, dan meningkatkan citra serta reputasi perusahaan di mata publik. Divisi ini menjadi jembatan komunikasi antara perusahaan dengan para pemangku kepentingan, termasuk pelanggan, mitra kerja, pemerintah, media massa, dan masyarakat luas. Melalui aktivitas komunikasi yang terarah, Divisi Humas memastikan pesan-pesan yang disampaikan perusahaan dapat diterima dengan baik oleh publik dan mendukung tujuan organisasi.", "application_deadline": "2025-12-07", "quota": 10, "registered": 15, "position_type": "Divisi Humas", "government_agency": null, "sub_government_agency": null, "angkatan": "3", "tahun": "2025"}