{"id": 741, "source_id": "a0810473-e506-4b43-bb1d-65d043c92a0b", "company_name": "Pelabuhan Perikanan Samudera Belawan (PPN Idi)", "province": "ACEH", "city": "KAB. ACEH TIMUR", "recommended_degree": "Teknologi Penangkapan Ikan, Teknologi Dan Manajemen Perikanan Tangkap, Pemanfaatan Sumberdaya Perikanan, Manajemen Sumberdaya Perairan, Penyuluhan Perikanan (Diploma, Sarjana)", "job_title": "Enumerator Kelautan dan Perikanan", "job_description": "1. Melakukan pendataan kapal perikanan yang masuk ke pelabuhan pangkalan\n2. Melakukan pendataan produksi ikan hasil tangkapan yang didaratkan dari kapal perikanan (kapal penangkap atau kapal pengangkut ikan)\n3. Mendokumentasikan kegiatan pembongkaran dan penimbangan ikan hasil tangkapan dan melakukan input hasil dokumentasi kedalam aplikasi PIPP.\n4. Melakukan pengumpulan data secara sampling untuk berat dan panjang, atau otolith untuk jenis sumber daya ikan tuna yang didaratkan di pelabuhan pangkalan, apabila diperlukan.\n5. Apabila tidak ada kegiatan pembongkaran ikan dari kapal perikanan di pelabuhan pangkalan, penyedia jasa dapat melakukan tugas lain yang berkaitan dengan pendataan kegiatan operasional kepelabuhanan perikanan.", "application_deadline": "2025-12-07", "quota": 1, "registered": 4, "position_type": "Enumerator Kelautan dan Perikanan", "government_agency": "Kementerian Kelautan dan Perikanan", "sub_government_agency": "Pelabuhan Perikanan Samudera Belawan (PPN Idi)", "angkatan": "3", "tahun": "2025"}