{"id": 8894, "source_id": "a07c5d33-9ed6-4c36-bb43-9147e2fb03b3", "company_name": "PT Jurnalindo Aksara Grafika", "province": "DKI JAKARTA", "city": "KOTA ADM. JAKARTA PUSAT", "recommended_degree": "Desain Komunikasi Visual, Jurnalistik, Pendidikan Seni, Pemasaran Digital, Ilmu Komunikasi (Sarjana)", "job_title": "Illustrator Intern", "job_description": "Deskripsi Lingkup Tugas: mengolah data dalam bentuk grafis, serta membuat asset ilustrasi dan grafis untuk keperluan media. Kualifikasi: memiliki ketertarikan pada bidang creative dan mampu mengoperasikan software editing, minimal Adobe Photoshop, Adobe Illustrator, Canva.", "application_deadline": "2025-12-07", "quota": 1, "registered": 5, "position_type": "Illustrator Intern", "government_agency": null, "sub_government_agency": null, "angkatan": "3", "tahun": "2025"}