{"id": 9611, "source_id": "a07efabd-d001-41f7-b822-3d96b5325fda", "company_name": "Mass Rapid Transit Jakarta Perseroda", "province": "DKI JAKARTA", "city": "KOTA ADM. JAKARTA PUSAT", "recommended_degree": "Teknik Industri, Manajemen Bisnis, Administrasi BIsnis, Manajemen (Sarjana)", "job_title": "Strategic Delivery and Corporate Performance Intern", "job_description": "1. Mendukung kegiatan perencanaan strategis perusahaan, seperti visi & misi, rencana jangka panjang perusahaan, dan perencanaan strategis lainnya;\n2. Membantu tim dalam proses riset dan kajian untuk kelangsungan bisnis perusahaan;\n3. Membantu tim dalam proses perencanaan, penyusunan, pengawasan, serta evaluasi KPI Korporasi dan Divisi; \n4. Terlibat dalam koordinasi dengan pihak internal maupun eksternal.", "application_deadline": "2025-12-07", "quota": 3, "registered": 8, "position_type": "Strategic Delivery and Corporate Performance Intern", "government_agency": null, "sub_government_agency": null, "angkatan": "3", "tahun": "2025"}