{"id": 9854, "source_id": "a07ecf53-59c7-45e6-aa3e-8dfc2af26dd0", "company_name": "Kementerian Desa dan Pembangunan Daerah Tertinggal Republik Indonesia", "province": "DKI JAKARTA", "city": "KOTA ADM. JAKARTA SELATAN", "recommended_degree": "Teknik Informatika, Administrasi Publik, Psikologi, Desain Komunikasi Visual, Hukum (Sarjana)", "job_title": "Staf Administrasi - Biro Organisasi, Sumber Daya Manusia dan Reformasi Birokrasi", "job_description": "Melaksanakan dukungan administrasi dan teknis dalam rangka penyiapan bahan serta pelaksanaan tugas lainnya di lingkungan Biro Organisasi, Sumber Daya Manusia dan Reformasi Birokrasi, Sekretariat Jenderal", "application_deadline": "2025-12-07", "quota": 2, "registered": 10, "position_type": "Staf Administrasi - Biro Organisasi, Sumber Daya Manusia dan Reformasi Birokrasi", "government_agency": "Kementerian Desa dan Pembangunan Daerah Tertinggal Republik Indonesia", "sub_government_agency": null, "angkatan": "3", "tahun": "2025"}